genhtml/__init__.py
genhtml/genhtml.py
genhtml/footers/biseau.py
genhtml/footers/default.py
genhtml/footers/dot-png.py
genhtml/footers/gif.py
genhtml/footers/plot-png.py
genhtml/footers/plot.py
genhtml/footers/png-image.py
genhtml/headers/default.py
genhtml/headers/graph.py
genhtml_markdown-1.0.9.dist-info/METADATA
genhtml_markdown-1.0.9.dist-info/RECORD
genhtml_markdown-1.0.9.dist-info/WHEEL
genhtml_markdown-1.0.9.dist-info/top_level.txt
