Metadata-Version: 2.1
Name: genhtml-markdown
Version: 1.0.9
Summary: bring python to markdown to generate HTML inline
Home-page: https://github.com/aluriak/genhtml-markdown
Author: Lucas Bourneuf
Author-email: lucas.bourneuf@laposte.net
License: GPL
Keywords: Markdown,plot,include,plugin,extension
Platform: UNKNOWN
Classifier: License :: OSI Approved :: MIT License
Classifier: Operating System :: OS Independent
Classifier: Programming Language :: Python :: 3
Classifier: Programming Language :: Python :: 3.6
Classifier: Programming Language :: Python :: 3.7
Classifier: Programming Language :: Python :: 3 :: Only
Classifier: Topic :: Software Development :: Libraries :: Python Modules
Requires-Dist: Markdown (==2.6.11)
Requires-Dist: Pillow (==5.2.0)
Requires-Dist: networkx (==2.2)
Requires-Dist: plotly (==3.2.1)
Requires-Dist: pydot (==1.2.4)
Requires-Dist: pytest (==3.8.0)
Requires-Dist: zest.releaser[recommended] (==6.15.2)
